onem2m/AE.py
onem2m/Config.py
onem2m/Constant.py
onem2m/__init__.py
onem2m-0.3.3.dist-info/METADATA
onem2m-0.3.3.dist-info/RECORD
onem2m-0.3.3.dist-info/WHEEL
onem2m-0.3.3.dist-info/top_level.txt
