Metadata-Version: 1.1
Name: onem2m
Version: 0.3.3
Summary: oneM2M ADN Client Lib
Home-page: https://github.com/kimkeehwan/onem2m_adn_lib_python
Author: Kim keehwan
Author-email: kimkeehwan@handysoft.co.kr
License: MIT
Platform: UNKNOWN
Classifier: Development Status :: 3 - Alpha
Classifier: Intended Audience :: Developers
Classifier: Topic :: Software Development :: Libraries
Classifier: License :: OSI Approved :: MIT License
Classifier: Programming Language :: Python :: 2.7
Classifier: Programming Language :: Python :: 3.5
